dstack_sdk-0.5.3.dist-info/METADATA
dstack_sdk-0.5.3.dist-info/WHEEL
dstack_sdk-0.5.3.dist-info/entry_points.txt
dstack_sdk/__init__.py
dstack_sdk/dstack_client.py
dstack_sdk/encrypt_env_vars.py
dstack_sdk/ethereum.py
dstack_sdk/get_compose_hash.py
dstack_sdk/py.typed
dstack_sdk/solana.py
dstack_sdk/verify_env_encrypt_public_key.py
dstack_sdk-0.5.3.dist-info/RECORD
