Metadata-Version: 2.1
Name: dstack-sdk
Version: 0.5.3
Summary: dstack SDK for Python
Author-Email: Leechael Yim <yanleech@gmail.com>, Kevin Wang <wy721@qq.com>
License: Apache-2.0
Requires-Python: >=3.10
Requires-Dist: httpx>=0.27.2
Requires-Dist: asyncio>=3.4.3
Requires-Dist: pydantic>=2.9.2
Requires-Dist: cryptography>=43.0.0
Provides-Extra: solana
Requires-Dist: solders; extra == "solana"
Provides-Extra: ethereum
Requires-Dist: web3; extra == "ethereum"
Provides-Extra: sol
Requires-Dist: solders; extra == "sol"
Provides-Extra: eth
Requires-Dist: web3; extra == "eth"
Provides-Extra: all
Requires-Dist: solders; extra == "all"
Requires-Dist: web3; extra == "all"
